{"name":"t:sections.footer.name","type":"footer","sections":{"smile_guarantee_support_QBidxW":{"type":"smile-guarantee-support","settings":{"title":"","margin_top":0,"margin_bottom":0,"padding_top":20,"padding_bottom":0,"margin_top_mobile":0,"margin_bottom_mobile":0,"padding_top_mobile":20,"padding_bottom_mobile":20}},"custom_footer_B6EYgh":{"type":"custom-footer","blocks":{"navigation_hccJaY":{"type":"navigation","settings":{"linklist":"shop"}},"navigation_CVDzDw":{"type":"navigation","settings":{"linklist":"about"}},"navigation_FmFVj8":{"type":"navigation","settings":{"linklist":"resources"}},"navigation_7NGwmP":{"type":"navigation","settings":{"linklist":"quick-links"}},"navigation_qc84py":{"type":"navigation","settings":{"linklist":"support"}},"title_image_iPyBie":{"type":"title_image","settings":{"logo":"shopify:\/\/shop_images\/SmileOptics_Blue.webp","rating_img":"shopify:\/\/shop_images\/rating.webp","text_rating":"4.8 Stars<br>   Kudobuzz™"}},"icon_8iUFx6":{"type":"icon","settings":{"social_icon":"shopify:\/\/shop_images\/da7ef6dd1302486c9a67baebe4b364bc.webp","url":"https:\/\/www.instagram.com\/smileopticsteeth\/"}},"icon_FKW6DC":{"type":"icon","settings":{"social_icon":"shopify:\/\/shop_images\/e0678ef25486466ba65ef6ad47b559e1.webp","url":"https:\/\/www.facebook.com\/smileopticsteeth"}},"icon_nGznja":{"type":"icon","settings":{"social_icon":"shopify:\/\/shop_images\/11062b_de6ea2753cd641be9085a85b55be7882_mv2.webp","url":"https:\/\/www.threads.net\/@smileopticsteeth"}},"icon_6JwzFa":{"type":"icon","settings":{"social_icon":"shopify:\/\/shop_images\/767689ba34f143a1a36e49b5f2fbe31a.webp","url":"https:\/\/www.pinterest.com\/smileoptics\/"}},"text_QJbyUw":{"type":"text","settings":{"caution":"<p>*These statements have not been evaluated by the Food and Drug Administration. These products are not intended to diagnose, treat, cure, or prevent any diseases. Results may vary.<\/p>","copyright":"© 2024 Smile LLC. All rights reserved •  1309 Cofeen Ave Ste 1200 Sheridan, WY 82801","privacy_policy":"shopify:\/\/pages\/privacy-policy","terms_conditions":"shopify:\/\/pages\/terms-conditions","website_disclaimer":"shopify:\/\/pages\/website-disclaimer"}}},"block_order":["navigation_hccJaY","navigation_CVDzDw","navigation_FmFVj8","navigation_7NGwmP","navigation_qc84py","title_image_iPyBie","icon_8iUFx6","icon_FKW6DC","icon_nGznja","icon_6JwzFa","text_QJbyUw"],"settings":{"rte":"<p>Sign Up & Get 20% Off Your First Purchase<\/p>","quote":"<p>No Spam. Ever. Because that sucks.<\/p>","btn_text":"Shop Bundles","url":"shopify:\/\/pages\/shop-bundles","nl__text":"Join!","nl__plcholder":"Enter Your Email","margin_top":0,"margin_bottom":0,"padding_top":0,"padding_bottom":0,"font_size":12,"margin_top-m":0,"margin_bottom-m":0,"padding_top-m":0,"padding_bottom-m":0}},"footer":{"type":"footer","disabled":true,"settings":{"color_scheme":"scheme-1","newsletter_enable":true,"newsletter_heading":"Subscribe to our emails","enable_follow_on_shop":true,"show_social":true,"enable_country_selector":true,"enable_language_selector":true,"payment_enable":true,"show_policy":false,"margin_top":0,"padding_top":36,"padding_bottom":36}}},"order":["smile_guarantee_support_QBidxW","custom_footer_B6EYgh","footer"]}